{
  "__commentExample": [
    {
      "__comment_name": "the name",
      "__comment_suitID": "the id of the suit (if you don't know keep 0), if a mod for a suit is uninstalled, it will be set to 0",
      "__comment_suitConfigOption": "0 Fixed (with the suit id set above), 1 random",
      "__comment_voiceFolder": "the name of the folder in pathToDllOfModInstalled/Audio/Voices",
      "__comment_volume": "volume (decimal like 0.65, 1.4, etc)",
      "__comment_voicePitch": "the pitch of the voice. Try to stay between 0.8 and 1.2, after that it's too much altered"
    }
  ],
  "configIdentities": [
    {
      "name": "Mathew Kelly",
      "suitID": 0,
      "suitConfigOption": 0,
      "voiceFolder": "Mathew_kelly",
      "volume": 0.2,
      "voicePitch": 1.0
    },
    {
      "name": "Amy Stake",
      "suitID": 0,
      "suitConfigOption": 1,
      "voiceFolder": "Mathew_kelly",
      "volume": 0.2,
      "voicePitch": 1.12
    },
    {
      "name": "Claire Annette",
      "suitID": 0,
      "suitConfigOption": 1,
      "voiceFolder": "Mathew_kelly",
      "volume": 0.2,
      "voicePitch": 1.13
    },
    {
      "name": "Clare Voyant",
      "suitID": 0,
      "suitConfigOption": 1,
      "voiceFolder": "Mathew_kelly",
      "volume": 0.2,
      "voicePitch": 1.14
    },
    {
      "name": "Ella Font",
      "suitID": 0,
      "suitConfigOption": 1,
      "voiceFolder": "Mathew_kelly",
      "volume": 0.2,
      "voicePitch": 1.15
    },
    {
      "name": "Felix Cited",
      "suitID": 0,
      "suitConfigOption": 1,
      "voiceFolder": "Mathew_kelly",
      "volume": 0.2,
      "voicePitch": 0.92
    },
    {
      "name": "Gerry Atrick",
      "suitID": 0,
      "suitConfigOption": 1,
      "voiceFolder": "Mathew_kelly",
      "volume": 0.2,
      "voicePitch": 0.91
    },
    {
      "name": "Harry Legg",
      "suitID": 0,
      "suitConfigOption": 1,
      "voiceFolder": "Mathew_kelly",
      "volume": 0.2,
      "voicePitch": 0.90
    },
    {
      "name": "Justin Case",
      "suitID": 0,
      "suitConfigOption": 1,
      "voiceFolder": "Mathew_kelly",
      "volume": 0.2,
      "voicePitch": 0.89
    },
    {
      "name": "Lee King",
      "suitID": 0,
      "suitConfigOption": 1,
      "voiceFolder": "Mathew_kelly",
      "volume": 0.2,
      "voicePitch": 0.88
    },
    {
      "name": "Luke Atmey",
      "suitID": 0,
      "suitConfigOption": 1,
      "voiceFolder": "Mathew_kelly",
      "volume": 0.2,
      "voicePitch": 0.87
    },
    {
      "name": "Manuel Labour",
      "suitID": 0,
      "suitConfigOption": 1,
      "voiceFolder": "Mathew_kelly",
      "volume": 0.2,
      "voicePitch": 0.86
    },
    {
      "name": "Mia Moore",
      "suitID": 0,
      "suitConfigOption": 1,
      "voiceFolder": "Mathew_kelly",
      "volume": 0.2,
      "voicePitch": 1.16
    },
    {
      "name": "Ophelia Pane",
      "suitID": 0,
      "suitConfigOption": 1,
      "voiceFolder": "Mathew_kelly",
      "volume": 0.2,
      "voicePitch": 1.17
    },
    {
      "name": "Paige Turner",
      "suitID": 0,
      "suitConfigOption": 1,
      "voiceFolder": "Mathew_kelly",
      "volume": 0.2,
      "voicePitch": 1.18
    },
    {
      "name": "Paul Atishon",
      "suitID": 0,
      "suitConfigOption": 1,
      "voiceFolder": "Mathew_kelly",
      "volume": 0.2,
      "voicePitch": 0.85
    },
    {
      "name": "Polly Esther",
      "suitID": 0,
      "suitConfigOption": 1,
      "voiceFolder": "Mathew_kelly",
      "volume": 0.2,
      "voicePitch": 1.2
    },
    {
      "name": "Robyn Banks",
      "suitID": 0,
      "suitConfigOption": 1,
      "voiceFolder": "Mathew_kelly",
      "volume": 0.2,
      "voicePitch": 1.19
    },
    {
      "name": "Terry Aki",
      "suitID": 0,
      "suitConfigOption": 1,
      "voiceFolder": "Mathew_kelly",
      "volume": 0.2,
      "voicePitch": 0.84
    },
    {
      "name": "Tim Burr",
      "suitID": 0,
      "suitConfigOption": 1,
      "voiceFolder": "Mathew_kelly",
      "volume": 0.2,
      "voicePitch": 0.83
    },
    {
      "name": "Toby Lerone",
      "suitID": 0,
      "suitConfigOption": 1,
      "voiceFolder": "Mathew_kelly",
      "volume": 0.2,
      "voicePitch": 0.82
    },
    {
      "name": "Uriel Lucky",
      "suitID": 0,
      "suitConfigOption": 1,
      "voiceFolder": "Mathew_kelly",
      "volume": 0.2,
      "voicePitch": 0.81
    },
    {
      "name": "Zoltan Pepper",
      "suitID": 0,
      "suitConfigOption": 1,
      "voiceFolder": "Mathew_kelly",
      "volume": 0.2,
      "voicePitch": 0.8
    }
  ]
}
